jsonxplode/__init__.py
jsonxplode/core.py
jsonxplode-1.2.1.dist-info/licenses/LICENSE
tests/__init__.py
tests/test_flatten.py
jsonxplode-1.2.1.dist-info/METADATA
jsonxplode-1.2.1.dist-info/WHEEL
jsonxplode-1.2.1.dist-info/top_level.txt
jsonxplode-1.2.1.dist-info/RECORD
