Metadata-Version: 2.4
Name: jsonxplode
Version: 1.2.1
Summary: Efficient JSON flattening for complex nested structures
Author: ThanatosDrive
Classifier: Programming Language :: Python :: 3
Classifier: License :: OSI Approved :: MIT License
Classifier: Operating System :: OS Independent
Requires-Python: >=3.6
License-File: LICENSE
Dynamic: author
Dynamic: classifier
Dynamic: description
Dynamic: description-content-type
Dynamic: license-file
Dynamic: requires-python
Dynamic: summary
